{
  "hash": "685766fd",
  "configHash": "56037ad9",
  "lockfileHash": "615a206a",
  "browserHash": "2114a581",
  "optimized": {
    "vue": {
      "src": "../../../../node_modules/vue/dist/vue.runtime.esm-bundler.js",
      "file": "vue.js",
      "fileHash": "db687c16",
      "needsInterop": false
    },
    "vitepress > @vue/devtools-api": {
      "src": "../../../../node_modules/@vue/devtools-api/lib/esm/index.js",
      "file": "vitepress___@vue_devtools-api.js",
      "fileHash": "3d97fc90",
      "needsInterop": false
    },
    "vitepress > @vueuse/core": {
      "src": "../../../../node_modules/@vueuse/core/index.mjs",
      "file": "vitepress___@vueuse_core.js",
      "fileHash": "1f10c338",
      "needsInterop": false
    }
  },
  "chunks": {
    "chunk-URVHZSMY": {
      "file": "chunk-URVHZSMY.js"
    }
  }
}